villa/__init__.py
villa/bot.py
villa/event.py
villa/exception.py
villa/handle.py
villa/log.py
villa/message.py
villa/models.py
villa/store.py
villa/typing.py
villa/utils.py
villa-0.8.0.dist-info/LICENSE
villa-0.8.0.dist-info/METADATA
villa-0.8.0.dist-info/WHEEL
villa-0.8.0.dist-info/RECORD
