Metadata-Version: 2.1
Name: villa
Version: 0.8.0
Summary: 米游社大别野Bot Python SDK。MiHoYo Villa Bot Python SDK.
Home-page: https://github.com/CMHopeSunshine/villa-py
License: MIT
Keywords: mihoyo,bot,villa
Author: CMHopeSunshine
Author-email: 277073121@qq.com
Requires-Python: >=3.8,<4.0
Classifier: License :: OSI Approved :: MIT License
Classifier: Programming Language :: Python :: 3
Classifier: Programming Language :: Python :: 3.8
Classifier: Programming Language :: Python :: 3.9
Classifier: Programming Language :: Python :: 3.10
Classifier: Programming Language :: Python :: 3.11
Requires-Dist: fastapi[uvicorn] (>=0.96.0,<0.97.0)
Requires-Dist: httpx (>=0.24.1,<0.25.0)
Requires-Dist: loguru (>=0.7.0,<0.8.0)
Requires-Dist: rsa (>=4.9,<5.0)
Requires-Dist: uvicorn (>=0.22.0,<0.23.0)
Project-URL: Documentation, https://github.com/CMHopeSunshine/villa-py
Project-URL: Repository, https://github.com/CMHopeSunshine/villa-py
